{
  "townName": "함평군",
  "nRows": 31,
  "hapVoters": 27154,
  "rows": [
    {
      "dong": "합계",
      "gubun": "",
      "voters": 27154,
      "votes": 21007,
      "A": 16054,
      "B": 2060,
      "c1": 617,
      "c2": 896,
      "c3": 333,
      "valid": 19960,
      "invalid": 1047,
      "abstain": 6147
    },
    {
      "dong": "거소투표",
      "gubun": "",
      "voters": 219,
      "votes": 201,
      "A": 135,
      "B": 29,
      "c1": 8,
      "c2": 10,
      "c3": 4,
      "valid": 186,
      "invalid": 15,
      "abstain": 18
    },
    {
      "dong": "관외사전투표",
      "gubun": "",
      "voters": 3362,
      "votes": 3362,
      "A": 2607,
      "B": 363,
      "c1": 118,
      "c2": 177,
      "c3": 33,
      "valid": 3298,
      "invalid": 64,
      "abstain": 0
    },
    {
      "dong": "함평읍",
      "gubun": "계",
      "voters": 6249,
      "votes": 4720,
      "A": 3675,
      "B": 465,
      "c1": 104,
      "c2": 207,
      "c3": 84,
      "valid": 4535,
      "invalid": 185,
      "abstain": 1529
    },
    {
      "dong": "함평읍",
      "gubun": "관내사전투표",
      "voters": 2920,
      "votes": 2919,
      "A": 2340,
      "B": 218,
      "c1": 58,
      "c2": 130,
      "c3": 51,
      "valid": 2797,
      "invalid": 122,
      "abstain": 1
    },
    {
      "dong": "함평읍",
      "gubun": "선거일투표",
      "voters": 3329,
      "votes": 1801,
      "A": 1335,
      "B": 247,
      "c1": 46,
      "c2": 77,
      "c3": 33,
      "valid": 1738,
      "invalid": 63,
      "abstain": 1528
    },
    {
      "dong": "손불면",
      "gubun": "계",
      "voters": 2500,
      "votes": 1897,
      "A": 1389,
      "B": 170,
      "c1": 63,
      "c2": 72,
      "c3": 34,
      "valid": 1728,
      "invalid": 169,
      "abstain": 603
    },
    {
      "dong": "손불면",
      "gubun": "관내사전투표",
      "voters": 1336,
      "votes": 1335,
      "A": 964,
      "B": 107,
      "c1": 55,
      "c2": 54,
      "c3": 21,
      "valid": 1201,
      "invalid": 134,
      "abstain": 1
    },
    {
      "dong": "손불면",
      "gubun": "선거일투표",
      "voters": 1164,
      "votes": 562,
      "A": 425,
      "B": 63,
      "c1": 8,
      "c2": 18,
      "c3": 13,
      "valid": 527,
      "invalid": 35,
      "abstain": 602
    },
    {
      "dong": "신광면",
      "gubun": "계",
      "voters": 1302,
      "votes": 1051,
      "A": 786,
      "B": 95,
      "c1": 26,
      "c2": 54,
      "c3": 20,
      "valid": 981,
      "invalid": 70,
      "abstain": 251
    },
    {
      "dong": "신광면",
      "gubun": "관내사전투표",
      "voters": 709,
      "votes": 709,
      "A": 537,
      "B": 58,
      "c1": 16,
      "c2": 38,
      "c3": 12,
      "valid": 661,
      "invalid": 48,
      "abstain": 0
    },
    {
      "dong": "신광면",
      "gubun": "선거일투표",
      "voters": 593,
      "votes": 342,
      "A": 249,
      "B": 37,
      "c1": 10,
      "c2": 16,
      "c3": 8,
      "valid": 320,
      "invalid": 22,
      "abstain": 251
    },
    {
      "dong": "학교면",
      "gubun": "계",
      "voters": 2658,
      "votes": 1910,
      "A": 1447,
      "B": 165,
      "c1": 58,
      "c2": 81,
      "c3": 36,
      "valid": 1787,
      "invalid": 123,
      "abstain": 748
    },
    {
      "dong": "학교면",
      "gubun": "관내사전투표",
      "voters": 1221,
      "votes": 1221,
      "A": 950,
      "B": 84,
      "c1": 30,
      "c2": 49,
      "c3": 20,
      "valid": 1133,
      "invalid": 88,
      "abstain": 0
    },
    {
      "dong": "학교면",
      "gubun": "선거일투표",
      "voters": 1437,
      "votes": 689,
      "A": 497,
      "B": 81,
      "c1": 28,
      "c2": 32,
      "c3": 16,
      "valid": 654,
      "invalid": 35,
      "abstain": 748
    },
    {
      "dong": "엄다면",
      "gubun": "계",
      "voters": 1415,
      "votes": 1061,
      "A": 830,
      "B": 107,
      "c1": 20,
      "c2": 32,
      "c3": 9,
      "valid": 998,
      "invalid": 63,
      "abstain": 354
    },
    {
      "dong": "엄다면",
      "gubun": "관내사전투표",
      "voters": 754,
      "votes": 754,
      "A": 606,
      "B": 57,
      "c1": 14,
      "c2": 22,
      "c3": 7,
      "valid": 706,
      "invalid": 48,
      "abstain": 0
    },
    {
      "dong": "엄다면",
      "gubun": "선거일투표",
      "voters": 661,
      "votes": 307,
      "A": 224,
      "B": 50,
      "c1": 6,
      "c2": 10,
      "c3": 2,
      "valid": 292,
      "invalid": 15,
      "abstain": 354
    },
    {
      "dong": "대동면",
      "gubun": "계",
      "voters": 2356,
      "votes": 1733,
      "A": 1298,
      "B": 193,
      "c1": 38,
      "c2": 76,
      "c3": 43,
      "valid": 1648,
      "invalid": 85,
      "abstain": 623
    },
    {
      "dong": "대동면",
      "gubun": "관내사전투표",
      "voters": 1070,
      "votes": 1070,
      "A": 828,
      "B": 91,
      "c1": 20,
      "c2": 42,
      "c3": 30,
      "valid": 1011,
      "invalid": 59,
      "abstain": 0
    },
    {
      "dong": "대동면",
      "gubun": "선거일투표",
      "voters": 1286,
      "votes": 663,
      "A": 470,
      "B": 102,
      "c1": 18,
      "c2": 34,
      "c3": 13,
      "valid": 637,
      "invalid": 26,
      "abstain": 623
    },
    {
      "dong": "나산면",
      "gubun": "계",
      "voters": 2098,
      "votes": 1526,
      "A": 1142,
      "B": 155,
      "c1": 59,
      "c2": 66,
      "c3": 16,
      "valid": 1438,
      "invalid": 88,
      "abstain": 572
    },
    {
      "dong": "나산면",
      "gubun": "관내사전투표",
      "voters": 982,
      "votes": 982,
      "A": 750,
      "B": 85,
      "c1": 37,
      "c2": 37,
      "c3": 5,
      "valid": 914,
      "invalid": 68,
      "abstain": 0
    },
    {
      "dong": "나산면",
      "gubun": "선거일투표",
      "voters": 1116,
      "votes": 544,
      "A": 392,
      "B": 70,
      "c1": 22,
      "c2": 29,
      "c3": 11,
      "valid": 524,
      "invalid": 20,
      "abstain": 572
    },
    {
      "dong": "해보면",
      "gubun": "계",
      "voters": 2202,
      "votes": 1577,
      "A": 1237,
      "B": 133,
      "c1": 51,
      "c2": 50,
      "c3": 18,
      "valid": 1489,
      "invalid": 88,
      "abstain": 625
    },
    {
      "dong": "해보면",
      "gubun": "관내사전투표",
      "voters": 1122,
      "votes": 1121,
      "A": 904,
      "B": 67,
      "c1": 34,
      "c2": 30,
      "c3": 10,
      "valid": 1045,
      "invalid": 76,
      "abstain": 1
    },
    {
      "dong": "해보면",
      "gubun": "선거일투표",
      "voters": 1080,
      "votes": 456,
      "A": 333,
      "B": 66,
      "c1": 17,
      "c2": 20,
      "c3": 8,
      "valid": 444,
      "invalid": 12,
      "abstain": 624
    },
    {
      "dong": "월야면",
      "gubun": "계",
      "voters": 2793,
      "votes": 1966,
      "A": 1507,
      "B": 185,
      "c1": 72,
      "c2": 70,
      "c3": 36,
      "valid": 1870,
      "invalid": 96,
      "abstain": 827
    },
    {
      "dong": "월야면",
      "gubun": "관내사전투표",
      "voters": 1245,
      "votes": 1245,
      "A": 968,
      "B": 99,
      "c1": 44,
      "c2": 47,
      "c3": 25,
      "valid": 1183,
      "invalid": 62,
      "abstain": 0
    },
    {
      "dong": "월야면",
      "gubun": "선거일투표",
      "voters": 1548,
      "votes": 721,
      "A": 539,
      "B": 86,
      "c1": 28,
      "c2": 23,
      "c3": 11,
      "valid": 687,
      "invalid": 34,
      "abstain": 827
    },
    {
      "dong": "잘못 투입·구분된 투표지",
      "gubun": "",
      "voters": 0,
      "votes": 3,
      "A": 1,
      "B": 0,
      "c1": 0,
      "c2": 1,
      "c3": 0,
      "valid": 2,
      "invalid": 1,
      "abstain": -3
    }
  ]
}